mariocard/__init__.py
mariocard.py-1.0.1.dist-info/LICENSE.txt
mariocard.py-1.0.1.dist-info/METADATA
mariocard.py-1.0.1.dist-info/WHEEL
mariocard.py-1.0.1.dist-info/top_level.txt
mariocard.py-1.0.1.dist-info/RECORD
