Metadata-Version: 2.1
Name: mariocard.py
Version: 1.0.1
Summary: This is simple maker for cards in discord bot.
Home-page: https://github.com/mario1842/mariocard.py/
Author: mario1842
Author-email: mario1842.info@gmail.com
License: MIT
Keywords: mariocard mariocard.py py discord level card welcome
Platform: UNKNOWN
Classifier: Development Status :: 5 - Production/Stable
Classifier: Intended Audience :: Education
Classifier: Operating System :: Microsoft :: Windows :: Windows 10
Classifier: License :: OSI Approved :: MIT License
Classifier: Programming Language :: Python :: 3
License-File: LICENSE.txt
Requires-Dist: Pillow
Requires-Dist: easy-pil
Requires-Dist: discord.py
